pydeen/__init__.py
pydeen/auth.py
pydeen/cloudevents.py
pydeen/const.py
pydeen/core.py
pydeen/exits.py
pydeen/files.py
pydeen/globals.py
pydeen/http.py
pydeen/menu.py
pydeen/odata.py
pydeen/pandas.py
pydeen/pyodata.py
pydeen/rest.py
pydeen/sap_abap.py
pydeen/sap_deeb.py
pydeen/sap_nwod.py
pydeen/service.py
pydeen/types.py
pydeen/utils.py
pydeen/websocket.py
pydeen/wsocket.py
pydeen-0.12.0.dist-info/LICENSE
pydeen-0.12.0.dist-info/METADATA
pydeen-0.12.0.dist-info/WHEEL
pydeen-0.12.0.dist-info/top_level.txt
pydeen-0.12.0.dist-info/RECORD
