Metadata-Version: 2.1
Name: pydeen
Version: 0.12.0
Summary: Python Data Engineer Enterprise Notebook
Author: MDJoerg (Joerg Mueller)
Author-email: <mdjoerg@joomp.de>
Keywords: python,data,data science,enterprise,analysis,toolbox,notebook
Classifier: Development Status :: 2 - Pre-Alpha
Classifier: Intended Audience :: Developers
Classifier: Programming Language :: Python :: 3
Classifier: Operating System :: Unix
Classifier: Operating System :: MacOS :: MacOS X
Classifier: Operating System :: Microsoft :: Windows
License-File: LICENSE
